setup.cfg
setup.py
requests_respectful/__init__.py
requests_respectful/exceptions.py
requests_respectful/globals.py
requests_respectful/respectful_requester.py
requests_respectful.egg-info/PKG-INFO
requests_respectful.egg-info/SOURCES.txt
requests_respectful.egg-info/dependency_links.txt
requests_respectful.egg-info/not-zip-safe
requests_respectful.egg-info/requires.txt
requests_respectful.egg-info/top_level.txt