Metadata-Version: 1.1
Name: requests-respectful
Version: 0.2.0
Summary: Minimalist wrapper on top of Requests to work within rate limits of any amount of services simultaneously. Parallel processing friendly.
Home-page: https://github.com/nbrochu/requests-respectful
Author: Nicholas Brochu
Author-email: info@nicholasbrochu.com
License: Apache License v2
Platform: UNKNOWN
Classifier: Development Status :: 5 - Production/Stable
Classifier: Intended Audience :: Developers
Classifier: Natural Language :: English
Classifier: License :: OSI Approved :: Apache Software License
Classifier: Programming Language :: Python
Classifier: Programming Language :: Python :: 2.7
Classifier: Programming Language :: Python :: 3
Classifier: Programming Language :: Python :: 3.2
Classifier: Programming Language :: Python :: 3.3
Classifier: Programming Language :: Python :: 3.4
Classifier: Programming Language :: Python :: 3.5
